ghga_service_chassis_lib/__init__.py
ghga_service_chassis_lib/__main__.py
ghga_service_chassis_lib/akafka.py
ghga_service_chassis_lib/api.py
ghga_service_chassis_lib/config.py
ghga_service_chassis_lib/mongo_connect.py
ghga_service_chassis_lib/object_storage_dao.py
ghga_service_chassis_lib/object_storage_dao_testing.py
ghga_service_chassis_lib/postgresql.py
ghga_service_chassis_lib/postgresql_testing.py
ghga_service_chassis_lib/pubsub.py
ghga_service_chassis_lib/pubsub_testing.py
ghga_service_chassis_lib/s3.py
ghga_service_chassis_lib/s3_testing.py
ghga_service_chassis_lib/utils.py
ghga_service_chassis_lib/test_files/__init__.py
ghga_service_chassis_lib/test_files/test_file1.yaml
ghga_service_chassis_lib/test_files/test_file2.yaml
ghga_service_chassis_lib/test_files/test_file3.yaml
ghga_service_chassis_lib/test_files/test_file4.yaml
tests/fixtures/__init__.py
tests/integration/__init__.py
tests/integration/test_api.py
tests/integration/test_mongo_connect.py
tests/integration/test_postgresql.py
tests/integration/test_pubsub.py
tests/integration/test_s3.py
tests/integration/fixtures/__init__.py
tests/integration/fixtures/amqp.py
tests/integration/fixtures/example_schema.json
tests/integration/fixtures/hello_world_test_app.py
tests/integration/fixtures/postgresql.py
tests/integration/fixtures/pubsub.py
tests/integration/fixtures/s3.py
tests/integration/fixtures/utils.py
tests/unit/__init__.py
tests/unit/test_akafka.py
tests/unit/test_config.py
tests/unit/test_object_storage_dao.py
tests/unit/test_utils.py
tests/unit/fixtures/__init__.py
tests/unit/fixtures/config.py
tests/unit/fixtures/config_env_var_sets.yaml
tests/unit/fixtures/object_storage_dao.py
tests/unit/fixtures/utils.py
ghga_service_chassis_lib-0.17.8.dist-info/LICENSE
ghga_service_chassis_lib-0.17.8.dist-info/METADATA
ghga_service_chassis_lib-0.17.8.dist-info/WHEEL
ghga_service_chassis_lib-0.17.8.dist-info/entry_points.txt
ghga_service_chassis_lib-0.17.8.dist-info/top_level.txt
ghga_service_chassis_lib-0.17.8.dist-info/RECORD
