Metadata-Version: 2.1
Name: ghga-service-chassis-lib
Version: 0.17.8
Summary: A library that contains the basic chassis functionality used in services of GHGA
Home-page: https://github.com/ghga-de/ghga-service-chassis-lib
Author: German Human Genome Phenome Archive (GHGA)
Author-email: contact@ghga.de
License: Apache 2.0
Classifier: Operating System :: POSIX :: Linux
Classifier: Programming Language :: Python :: 3.9
Classifier: License :: OSI Approved :: Apache Software License
Classifier: Topic :: Internet :: WWW/HTTP :: HTTP Servers
Classifier: Topic :: Scientific/Engineering :: Bio-Informatics
Requires-Python: >=3.9
License-File: LICENSE
Requires-Dist: pydantic ==1.10.6
Requires-Dist: PyYAML ==6.0
Provides-Extra: all
Requires-Dist: fastapi ==0.89.1 ; extra == 'all'
Requires-Dist: uvicorn[standard] ==0.20.0 ; extra == 'all'
Requires-Dist: httpyexpect ==0.2.4 ; extra == 'all'
Requires-Dist: requests ==2.28.1 ; extra == 'all'
Requires-Dist: pika ==1.3.1 ; extra == 'all'
Requires-Dist: jsonschema ==4.17.3 ; extra == 'all'
Requires-Dist: kafka-python ==2.0.2 ; extra == 'all'
Requires-Dist: motor ==3.1.1 ; extra == 'all'
Requires-Dist: sqlalchemy ==1.4.46 ; extra == 'all'
Requires-Dist: asyncpg ==0.27.0 ; extra == 'all'
Requires-Dist: psycopg2 ==2.9.5 ; extra == 'all'
Requires-Dist: pytest ==7.2.0 ; extra == 'all'
Requires-Dist: pytest-asyncio ==0.20.3 ; extra == 'all'
Requires-Dist: pytest-cov ==4.0.0 ; extra == 'all'
Requires-Dist: mypy ==1.0.0 ; extra == 'all'
Requires-Dist: mypy-extensions ==1.0.0 ; extra == 'all'
Requires-Dist: types-requests ==2.28.11.7 ; extra == 'all'
Requires-Dist: pylint ==2.16.4 ; extra == 'all'
Requires-Dist: click ==8.1.3 ; extra == 'all'
Requires-Dist: black ==23.1.0 ; extra == 'all'
Requires-Dist: flake8 ==6.0.0 ; extra == 'all'
Requires-Dist: isort ==5.12.0 ; extra == 'all'
Requires-Dist: bandit ==1.7.4 ; extra == 'all'
Requires-Dist: pre-commit ==3.1.1 ; extra == 'all'
Requires-Dist: mkdocs ==1.4.2 ; extra == 'all'
Requires-Dist: mkdocs-autorefs ==0.4.1 ; extra == 'all'
Requires-Dist: mkdocs-material ==9.0.3 ; extra == 'all'
Requires-Dist: mkdocs-material-extensions ==1.1.1 ; extra == 'all'
Requires-Dist: mkdocstrings ==0.19.1 ; extra == 'all'
Requires-Dist: mkdocstrings-python-legacy ==0.2.3 ; extra == 'all'
Requires-Dist: testcontainers[kafka,mongo,postgresql] ==3.4.1 ; extra == 'all'
Requires-Dist: typer ==0.7.0 ; extra == 'all'
Requires-Dist: sqlalchemy-utils ==0.39.0 ; extra == 'all'
Requires-Dist: sqlalchemy-stubs ==0.4 ; extra == 'all'
Requires-Dist: httpx ==0.23.3 ; extra == 'all'
Requires-Dist: boto3 ==1.26.46 ; extra == 'all'
Requires-Dist: botocore ==1.29.47 ; extra == 'all'
Provides-Extra: api
Requires-Dist: fastapi ==0.89.1 ; extra == 'api'
Requires-Dist: uvicorn[standard] ==0.20.0 ; extra == 'api'
Requires-Dist: httpyexpect ==0.2.4 ; extra == 'api'
Requires-Dist: requests ==2.28.1 ; extra == 'api'
Provides-Extra: dev
Requires-Dist: pytest ==7.2.0 ; extra == 'dev'
Requires-Dist: pytest-asyncio ==0.20.3 ; extra == 'dev'
Requires-Dist: pytest-cov ==4.0.0 ; extra == 'dev'
Requires-Dist: mypy ==1.0.0 ; extra == 'dev'
Requires-Dist: mypy-extensions ==1.0.0 ; extra == 'dev'
Requires-Dist: types-requests ==2.28.11.7 ; extra == 'dev'
Requires-Dist: pylint ==2.16.4 ; extra == 'dev'
Requires-Dist: click ==8.1.3 ; extra == 'dev'
Requires-Dist: black ==23.1.0 ; extra == 'dev'
Requires-Dist: flake8 ==6.0.0 ; extra == 'dev'
Requires-Dist: isort ==5.12.0 ; extra == 'dev'
Requires-Dist: bandit ==1.7.4 ; extra == 'dev'
Requires-Dist: pre-commit ==3.1.1 ; extra == 'dev'
Requires-Dist: mkdocs ==1.4.2 ; extra == 'dev'
Requires-Dist: mkdocs-autorefs ==0.4.1 ; extra == 'dev'
Requires-Dist: mkdocs-material ==9.0.3 ; extra == 'dev'
Requires-Dist: mkdocs-material-extensions ==1.1.1 ; extra == 'dev'
Requires-Dist: mkdocstrings ==0.19.1 ; extra == 'dev'
Requires-Dist: mkdocstrings-python-legacy ==0.2.3 ; extra == 'dev'
Requires-Dist: testcontainers[kafka,mongo,postgresql] ==3.4.1 ; extra == 'dev'
Requires-Dist: typer ==0.7.0 ; extra == 'dev'
Requires-Dist: sqlalchemy-utils ==0.39.0 ; extra == 'dev'
Requires-Dist: sqlalchemy-stubs ==0.4 ; extra == 'dev'
Requires-Dist: httpx ==0.23.3 ; extra == 'dev'
Provides-Extra: kafka
Requires-Dist: kafka-python ==2.0.2 ; extra == 'kafka'
Requires-Dist: jsonschema ==4.17.3 ; extra == 'kafka'
Provides-Extra: mongo_connect
Requires-Dist: motor ==3.1.1 ; extra == 'mongo_connect'
Provides-Extra: object_storage_dao
Provides-Extra: postgresql
Requires-Dist: sqlalchemy ==1.4.46 ; extra == 'postgresql'
Requires-Dist: asyncpg ==0.27.0 ; extra == 'postgresql'
Requires-Dist: psycopg2 ==2.9.5 ; extra == 'postgresql'
Provides-Extra: pubsub
Requires-Dist: pika ==1.3.1 ; extra == 'pubsub'
Requires-Dist: jsonschema ==4.17.3 ; extra == 'pubsub'
Provides-Extra: s3
Requires-Dist: boto3 ==1.26.46 ; extra == 's3'
Requires-Dist: botocore ==1.29.47 ; extra == 's3'
